odoo/addons/ssi_employee_business_trip/README.rst
odoo/addons/ssi_employee_business_trip/__init__.py
odoo/addons/ssi_employee_business_trip/__manifest__.py
odoo/addons/ssi_employee_business_trip/data/approval_template_data.xml
odoo/addons/ssi_employee_business_trip/data/base_automation_data.xml
odoo/addons/ssi_employee_business_trip/data/ir_actions_server_data.xml
odoo/addons/ssi_employee_business_trip/data/ir_sequence_data.xml
odoo/addons/ssi_employee_business_trip/data/policy_template_data.xml
odoo/addons/ssi_employee_business_trip/data/sequence_template_data.xml
odoo/addons/ssi_employee_business_trip/i18n/ssi_employee_business_trip.pot
odoo/addons/ssi_employee_business_trip/models/__init__.py
odoo/addons/ssi_employee_business_trip/models/employee_business_trip.py
odoo/addons/ssi_employee_business_trip/models/employee_business_trip_per_diem.py
odoo/addons/ssi_employee_business_trip/models/employee_business_trip_tax.py
odoo/addons/ssi_employee_business_trip/models/employee_business_trip_type.py
odoo/addons/ssi_employee_business_trip/security/ir.model.access.csv
odoo/addons/ssi_employee_business_trip/security/ir_module_category_data.xml
odoo/addons/ssi_employee_business_trip/security/ir_rule_data.xml
odoo/addons/ssi_employee_business_trip/security/res_group_data.xml
odoo/addons/ssi_employee_business_trip/static/description/icon.png
odoo/addons/ssi_employee_business_trip/views/employee_business_trip_type_views.xml
odoo/addons/ssi_employee_business_trip/views/employee_business_trip_views.xml
odoo14_addon_ssi_employee_business_trip-14.0.2.3.0.dist-info/METADATA
odoo14_addon_ssi_employee_business_trip-14.0.2.3.0.dist-info/WHEEL
odoo14_addon_ssi_employee_business_trip-14.0.2.3.0.dist-info/top_level.txt
odoo14_addon_ssi_employee_business_trip-14.0.2.3.0.dist-info/RECORD
